<annotation>
	<folder>train</folder>
	<filename>57.jpg</filename>
	<path>D:\CoolThings\models\models\research\object_detection\images\train\57.jpg</path>
	<source>
		<database>Unknown</database>
	</source>
	<size>
		<width>3840</width>
		<height>2178</height>
		<depth>3</depth>
	</size>
	<segmented>0</segmented>
	<object>
		<name>Drone</name>
		<pose>Unspecified</pose>
		<truncated>0</truncated>
		<difficult>0</difficult>
		<bndbox>
			<xmin>1548</xmin>
			<ymin>816</ymin>
			<xmax>2083</xmax>
			<ymax>1069</ymax>
		</bndbox>
	</object>
</annotation>
